piplexed/__init__.py
piplexed/app.py
piplexed/cli.py
piplexed/utils.py
piplexed/version.py
piplexed/display/__init__.py
piplexed/display/print_table.py
piplexed/display/print_tree.py
piplexed/pypi/__init__.py
piplexed/pypi/pypi_info.py
piplexed/venvs/__init__.py
piplexed/venvs/pipx_venvs.py
piplexed/venvs/uv_venvs.py
piplexed-1.1.0.dist-info/METADATA
piplexed-1.1.0.dist-info/WHEEL
piplexed-1.1.0.dist-info/entry_points.txt
piplexed-1.1.0.dist-info/licenses/LICENSE.txt
piplexed-1.1.0.dist-info/RECORD
