Metadata-Version: 2.3
Name: piplexed
Version: 1.1.0
Summary: Find outdated python packages installed with pipx
Project-URL: Documentation, https://aj-white.github.io/piplexed/
Project-URL: Issues, https://github.com/aj-white/piplexed/issues
Project-URL: Source, https://github.com/aj-white/piplexed
Author-email: Andrew White <white-aj@outlook.com>
License: MIT
Keywords:  dependency,cli,pipx
Classifier: Development Status :: 4 - Beta
Classifier: Programming Language :: Python
Classifier: Programming Language :: Python :: 3.9
Classifier: Programming Language :: Python :: 3.10
Classifier: Programming Language :: Python :: 3.11
Classifier: Programming Language :: Python :: 3.12
Classifier: Programming Language :: Python :: 3.13
Classifier: Programming Language :: Python :: Implementation :: CPython
Requires-Python: >=3.9
Requires-Dist: packaging
Requires-Dist: platformdirs
Requires-Dist: pypi-simple>=1.1.0
Requires-Dist: rich
Requires-Dist: typer
